logger/__init__.py
logger/formatter.py
logging_profcomff-2023.10.29.dist-info/LICENSE
logging_profcomff-2023.10.29.dist-info/METADATA
logging_profcomff-2023.10.29.dist-info/WHEEL
logging_profcomff-2023.10.29.dist-info/top_level.txt
logging_profcomff-2023.10.29.dist-info/RECORD
