Metadata-Version: 2.1
Name: logging-profcomff
Version: 2023.10.29
Home-page: https://github.com/profcomff/logging-lib
Author: Semyon Grigoriev
Classifier: Programming Language :: Python :: 3.11
License-File: LICENSE
Requires-Dist: setuptools
